odoo/addons/fieldservice_equipment_type/README.rst
odoo/addons/fieldservice_equipment_type/__init__.py
odoo/addons/fieldservice_equipment_type/__manifest__.py
odoo/addons/fieldservice_equipment_type/i18n/fieldservice_equipment_type.pot
odoo/addons/fieldservice_equipment_type/i18n/it.po
odoo/addons/fieldservice_equipment_type/models/__init__.py
odoo/addons/fieldservice_equipment_type/models/fsm_equipment.py
odoo/addons/fieldservice_equipment_type/models/fsm_equipment_type.py
odoo/addons/fieldservice_equipment_type/readme/CONTRIBUTORS.rst
odoo/addons/fieldservice_equipment_type/readme/DESCRIPTION.rst
odoo/addons/fieldservice_equipment_type/security/ir.model.access.csv
odoo/addons/fieldservice_equipment_type/static/description/icon.png
odoo/addons/fieldservice_equipment_type/static/description/index.html
odoo/addons/fieldservice_equipment_type/tests/__init__.py
odoo/addons/fieldservice_equipment_type/tests/fsm_equipment_type.py
odoo/addons/fieldservice_equipment_type/views/fsm_equipment.xml
odoo/addons/fieldservice_equipment_type/views/fsm_equipment_type.xml
odoo14_addon_fieldservice_equipment_type-14.0.1.0.1.dev5.dist-info/METADATA
odoo14_addon_fieldservice_equipment_type-14.0.1.0.1.dev5.dist-info/WHEEL
odoo14_addon_fieldservice_equipment_type-14.0.1.0.1.dev5.dist-info/top_level.txt
odoo14_addon_fieldservice_equipment_type-14.0.1.0.1.dev5.dist-info/RECORD
